flask_discord/__init__.py
flask_discord/_http.py
flask_discord/client.py
flask_discord/configs.py
flask_discord/exceptions.py
flask_discord/utils.py
flask_discord/models/__init__.py
flask_discord/models/base.py
flask_discord/models/connections.py
flask_discord/models/guild.py
flask_discord/models/integration.py
flask_discord/models/user.py
flask_discord/types/__init__.py
flask_discord/types/permissions.py
tests/__init__.py
tests/test_app.py
tests/test_factory_app.py
Flask_Discord-0.1.69.dist-info/LICENSE
Flask_Discord-0.1.69.dist-info/METADATA
Flask_Discord-0.1.69.dist-info/WHEEL
Flask_Discord-0.1.69.dist-info/top_level.txt
Flask_Discord-0.1.69.dist-info/RECORD
