Metadata-Version: 2.1
Name: Flask-Discord
Version: 0.1.69
Summary: Discord OAuth2 extension for Flask.
Home-page: https://github.com/thec0sm0s/Flask-Discord
Author: □ | The Cosmos
Author-email: deepakrajko14@gmail.com
License: MIT
Platform: any
Classifier: Framework :: Flask
Classifier: Environment :: Web Environment
Classifier: Intended Audience :: Developers
Classifier: License :: OSI Approved :: MIT License
Classifier: Operating System :: OS Independent
Classifier: Programming Language :: Python
Classifier: Topic :: Internet :: WWW/HTTP :: Dynamic Content
Classifier: Topic :: Software Development :: Libraries :: Python Modules
Provides-Extra: docs
License-File: LICENSE
